statsd/__init__.py
statsd/tests.py
statsd/client/__init__.py
statsd/client/base.py
statsd/client/stream.py
statsd/client/timer.py
statsd/client/udp.py
statsd/defaults/__init__.py
statsd/defaults/django.py
statsd/defaults/env.py
statsd-4.0.0.dist-info/AUTHORS
statsd-4.0.0.dist-info/LICENSE
statsd-4.0.0.dist-info/METADATA
statsd-4.0.0.dist-info/WHEEL
statsd-4.0.0.dist-info/top_level.txt
statsd-4.0.0.dist-info/RECORD
